{
  "version": 2,
  "_referencia_tipos": {
    "Tipo1": "FCC",
    "Tipo2": "URBASER",
    "Tipo3": "MIXTO",
    "Tipo4": "CLD",
    "Tipo5": "VALORIZA",
    "Tipo6": "LUN-SAB 6-0"
  },
  "mensajes_globales": [
    {
      "id": "global-msg-2",
      "titulo": "GLOBAL",
      "texto": "Jose Antonio Martinez",
      "activo": false,
      "obligatorio": false,
      "prioridad": 10,
      "fecha_inicio": "",
      "fecha_fin": "",
      "icono": "🛠",
      "boton_aceptar": "Aceptar",
      "boton_cancelar": "Mas tarde",
      "mostrar_cancelar": false,
      "accion": "",
      "ano": ""
    },
    {
      "id": "global-20260411-072841564",
      "titulo": "GLOBAL",
      "texto": "Escribe aqui el mensaje.",
      "activo": true,
      "obligatorio": true,
      "prioridad": 10,
      "fecha_inicio": "11\/04\/2026",
      "fecha_fin": "18\/04\/2026",
      "icono": "📢",
      "boton_aceptar": "Aceptar",
      "boton_cancelar": "Mas tarde",
      "mostrar_cancelar": false,
      "accion": "",
      "ano": ""
    }
  ],
  "mensajes_por_empresa": {
    "Tipo1": [
      {
        "id": "tipo1-msg-1",
        "titulo": "Aviso FCC",
        "texto": "kljglksdafgklsdflkgjlksdfjgkljsdfkljgkldfjgkldfjgkljdfslkgjkldfjgbkldfsjgkljdfsklgjdklfjgkldfjgklfjdgkljdfklgjdfkl",
        "activo": true,
        "obligatorio": true,
        "prioridad": 10,
        "fecha_inicio": "",
        "fecha_fin": "",
        "icono": "📅",
        "boton_aceptar": "Aceptar",
        "boton_cancelar": "Mas tarde",
        "mostrar_cancelar": false,
        "accion": "",
        "ano": ""
      }
    ],
    "Tipo2": [],
    "Tipo3": [],
    "Tipo4": [],
    "Tipo5": [],
    "Tipo6": []
  }
}